<?xml version="1.0" encoding="utf-8"?>
<odoo>
    <data noupdate="0">

        <record id="sdi_host_active" model="ir.config_parameter">
            <field name="key">sdi_active_host</field>
            <field name="value">https://active_host.com</field>
        </record>

        <record id="sdi_host_passive" model="ir.config_parameter">
            <field name="key">sdi_passive_host</field>
            <field name="value">https://passive_host.com</field>
        </record>

    </data>
</odoo>
